basilisp_nrepl_async/__init__.py
basilisp_nrepl_async/nrepl_server.lpy
basilisp_nrepl_async/utils.lpy
basilisp_nrepl_async-0.1.1.dist-info/LICENSE
basilisp_nrepl_async-0.1.1.dist-info/METADATA
basilisp_nrepl_async-0.1.1.dist-info/WHEEL
basilisp_nrepl_async-0.1.1.dist-info/RECORD
