Metadata-Version: 2.1
Name: basilisp-nrepl-async
Version: 0.1.1
Summary: 
Author: ikappaki
Author-email: ikappaki@users.noreply.github.com
Requires-Python: >=3.9,<4.0
Classifier: Programming Language :: Python :: 3
Classifier: Programming Language :: Python :: 3.9
Classifier: Programming Language :: Python :: 3.10
Classifier: Programming Language :: Python :: 3.11
Classifier: Programming Language :: Python :: 3.12
Classifier: Programming Language :: Python :: 3.13
Requires-Dist: basilisp (>=0.3.2)
